fastapi_proxiedheadersmiddleware/__init__.py
fastapi_proxiedheadersmiddleware-0.9.0.dist-info/COPYING
fastapi_proxiedheadersmiddleware-0.9.0.dist-info/METADATA
fastapi_proxiedheadersmiddleware-0.9.0.dist-info/WHEEL
fastapi_proxiedheadersmiddleware-0.9.0.dist-info/top_level.txt
fastapi_proxiedheadersmiddleware-0.9.0.dist-info/RECORD
