Metadata-Version: 2.1
Name: fastapi-proxiedheadersmiddleware
Version: 0.9.0
Summary: Middleware for fastapi allowing it to respect X-Forwarded-... headers set by proxies.
Home-page: https://gitlab.developers.cam.ac.uk/uis/devops/lib/fastapi-proxiedheadersmiddleware
Author: University of Cambridge Information Services
Author-email: devops+fastapi-proxiedheadersmiddleware@uis.cam.ac.uk
License: MIT
Platform: UNKNOWN
Classifier: Programming Language :: Python :: 3
Classifier: License :: OSI Approved :: MIT License
Classifier: Development Status :: 4 - Beta
Classifier: Intended Audience :: Developers
Classifier: License :: OSI Approved :: MIT License
Classifier: Operating System :: OS Independent
License-File: COPYING
Requires-Dist: fastapi (>=0.68.0)
Requires-Dist: requests (~=2.26)
